<?xml version="1.0" encoding="UTF-8"?><xfdf xmlns="http://ns.adobe.com/xfdf/" xml:space="preserve"><fields/><annots><highlight style="solid" width="0" color="#FACD5A" flags="print" name="002a131503671416-13b58e5548e7970b" page="115" coords="48.9215,523.219,459.362,523.219,48.9215,507.903,459.362,507.903" rect="47.3899,506.371,460.894,524.751" title="fangxuyuan">
			<defaultappearance>//Helvetica 12 Tf 0 g</defaultappearance>
			<apref blend-mode="multiply" y="524.751" x="47.3899" gennum="0" objnum="5142"/>
		</highlight><highlight style="solid" width="0" color="#C885DA" flags="print" name="002a13590367145a-13b58e1148e796c7" page="135" coords="139.699,173.299,454.553,173.299,139.699,159.258,454.553,159.258,48.602,157.403,368.233,157.403,48.602,143.585,368.233,143.585" rect="47.2203,142.204,455.957,174.703" title="fangxuyuan">
			<defaultappearance>//Helvetica 12 Tf 0 g</defaultappearance>
			<apref blend-mode="multiply" y="174.703" x="47.2203" gennum="0" objnum="5210"/>
		</highlight><highlight style="solid" width="0" color="#7CC868" flags="print" name="002a139c0367149d-13b58dce48e79684" page="136" coords="396.674,157.462,457.077,157.462,396.674,143.585,457.077,143.585,51.0906,141.726,99.3957,141.726,51.0906,128.129,99.3957,128.129" rect="49.7309,126.769,458.464,158.85" title="fangxuyuan">
			<defaultappearance>//Helvetica 12 Tf 0 g</defaultappearance>
			<apref blend-mode="multiply" y="158.85" x="49.7309" gennum="0" objnum="5277"/>
		</highlight><highlight style="solid" width="0" color="#7CC868" flags="print" name="002a13df036714e0-13b58d8b48e79641" page="164" coords="146.445,529.462,309.142,529.462,146.445,513.876,309.142,513.876" rect="144.886,512.317,310.7,531.02" title="fangxuyuan">
			<defaultappearance>//Helvetica 12 Tf 0 g</defaultappearance>
			<apref blend-mode="multiply" y="531.02" x="144.886" gennum="0" objnum="5344"/>
		</highlight><highlight style="solid" width="0" color="#7CC868" flags="print" name="002a142303671524-13b58d4748e795fd" page="172" coords="168.878,530.357,351.085,530.357,168.878,508.402,351.085,508.402" rect="166.682,506.206,353.281,532.553" title="fangxuyuan">
			<defaultappearance>//Helvetica 12 Tf 0 g</defaultappearance>
			<apref blend-mode="multiply" y="532.553" x="166.682" gennum="0" objnum="5412"/>
		</highlight><highlight style="solid" width="0" color="#7CC868" flags="print" name="002a146603671567-13b58d0448e795ba" page="175" coords="63.6823,79.8962,231.244,79.8962,63.6823,59.635,231.244,59.635,64.1099,64.3654,338.212,64.3654,64.1099,45.2002,338.212,45.2002" rect="61.6562,43.2837,340.129,81.9223" title="fangxuyuan">
			<defaultappearance>//Helvetica 12 Tf 0 g</defaultappearance>
			<apref blend-mode="multiply" y="81.9223" x="61.6562" gennum="0" objnum="5479"/>
		</highlight><highlight style="solid" width="0" color="#7CC868" flags="print" name="002a14a9036715aa-13b58cc148e79577" page="177" coords="69.7328,100.675,327.261,100.675,69.7328,85.9383,327.261,85.9383" rect="68.2591,84.4647,328.735,102.149" title="fangxuyuan">
			<defaultappearance>//Helvetica 12 Tf 0 g</defaultappearance>
			<apref blend-mode="multiply" y="102.149" x="68.2591" gennum="0" objnum="5546"/>
		</highlight><highlight style="solid" width="0" color="#7CC868" flags="print" name="002a14ec036715ed-13b58c7e48e79534" page="178" coords="70.057,572.162,290.289,572.162,70.057,557.382,290.289,557.382" rect="68.579,555.904,291.767,573.64" title="fangxuyuan">
			<defaultappearance>//Helvetica 12 Tf 0 g</defaultappearance>
			<apref blend-mode="multiply" y="573.64" x="68.579" gennum="0" objnum="5613"/>
		</highlight><highlight style="solid" width="0" color="#7CC868" flags="print" name="002a14ed036715ee-13b58c7d48e79533" page="178" coords="70.2166,558.523,157.25,558.523,70.2166,542.644,157.25,542.644" rect="68.6287,541.056,158.838,560.111" title="fangxuyuan">
			<defaultappearance>//Helvetica 12 Tf 0 g</defaultappearance>
			<apref blend-mode="multiply" y="560.111" x="68.6287" gennum="0" objnum="5614"/>
		</highlight><highlight style="solid" width="0" color="#7CC868" flags="print" name="002a156c0367166d-13b58bfe48e794b4" page="181" coords="160.718,106.767,461.96,106.767,160.718,91.4444,461.96,91.4444" rect="159.186,89.9122,463.492,108.299" title="fangxuyuan">
			<defaultappearance>//Helvetica 12 Tf 0 g</defaultappearance>
			<apref blend-mode="multiply" y="108.299" x="159.186" gennum="0" objnum="5741"/>
		</highlight><highlight style="solid" width="0" color="#7CC868" flags="print" name="002a15b0036716b1-13b58bba48e79470" page="228" coords="69.2538,210.269,455.953,210.269,69.2538,196.344,455.953,196.344,49.8033,194.964,154.585,194.964,49.8033,180.971,154.585,180.971" rect="48.404,179.572,457.346,211.662" title="fangxuyuan">
			<defaultappearance>//Helvetica 12 Tf 0 g</defaultappearance>
			<apref blend-mode="multiply" y="211.662" x="48.404" gennum="0" objnum="5809"/>
		</highlight><highlight style="solid" width="0" color="#7CC868" flags="print" name="002a15f3036716f4-13b58b7748e7942d" page="234" coords="71.7547,66.1703,275.53,66.1703,71.7547,52.1316,275.53,52.1316" rect="70.3508,50.7277,276.934,67.5742" title="fangxuyuan">
			<defaultappearance>//Helvetica 12 Tf 0 g</defaultappearance>
			<apref blend-mode="multiply" y="67.5742" x="70.3508" gennum="0" objnum="5876"/>
		</highlight><highlight style="solid" width="0" color="#7CC868" flags="print" name="002a163703671738-13b58b3348e793e9" page="283" coords="68.9767,541.674,454.146,541.674,68.9767,530.328,454.146,530.328,48.5767,527.012,332.305,527.012,48.5767,511.56,332.305,511.56" rect="47.0315,510.015,455.28,542.809" title="fangxuyuan">
			<defaultappearance>//Helvetica 12 Tf 0 g</defaultappearance>
			<apref blend-mode="multiply" y="542.809" x="47.0315" gennum="0" objnum="5944"/>
		</highlight></annots><pages><defmtx matrix="1,0,0,-1,0,657.404"/><pgmtx matrix="1,0,0,-1,0,654.525" page="2"/><pgmtx matrix="1,0,0,-1,0,654.525" page="3"/><pgmtx matrix="1,0,0,-1,0,654.525" page="4"/><pgmtx matrix="1,0,0,-1,0,654.525" page="5"/><pgmtx matrix="1,0,0,-1,0,654.525" page="6"/><pgmtx matrix="1,0,0,-1,0,654.525" page="7"/><pgmtx matrix="1,0,0,-1,0,654.525" page="8"/><pgmtx matrix="1,0,0,-1,0,654.525" page="9"/><pgmtx matrix="1,0,0,-1,0,654.525" page="10"/><pgmtx matrix="1,0,0,-1,0,654.525" page="11"/><pgmtx matrix="1,0,0,-1,0,654.525" page="12"/><pgmtx matrix="1,0,0,-1,0,654.525" page="13"/><pgmtx matrix="1,0,0,-1,0,654.525" page="14"/><pgmtx matrix="1,0,0,-1,0,654.525" page="15"/><pgmtx matrix="1,0,0,-1,0,654.525" page="16"/><pgmtx matrix="1,0,0,-1,0,654.525" page="17"/><pgmtx matrix="1,0,0,-1,0,654.525" page="18"/><pgmtx matrix="1,0,0,-1,0,654.525" page="19"/><pgmtx matrix="1,0,0,-1,0,654.525" page="20"/><pgmtx matrix="1,0,0,-1,0,654.525" page="21"/><pgmtx matrix="1,0,0,-1,0,654.525" page="22"/><pgmtx matrix="1,0,0,-1,0,654.525" page="23"/><pgmtx matrix="1,0,0,-1,0,654.525" page="24"/><pgmtx matrix="1,0,0,-1,0,654.525" page="25"/><pgmtx matrix="1,0,0,-1,0,654.525" page="26"/><pgmtx matrix="1,0,0,-1,0,654.525" page="27"/><pgmtx matrix="1,0,0,-1,0,654.525" page="28"/><pgmtx matrix="1,0,0,-1,0,654.525" page="29"/><pgmtx matrix="1,0,0,-1,0,654.525" page="30"/><pgmtx matrix="1,0,0,-1,0,654.525" page="31"/><pgmtx matrix="1,0,0,-1,0,654.525" page="32"/><pgmtx matrix="1,0,0,-1,0,654.525" page="33"/><pgmtx matrix="1,0,0,-1,0,654.525" page="34"/><pgmtx matrix="1,0,0,-1,0,654.525" page="35"/><pgmtx matrix="1,0,0,-1,0,654.525" page="36"/><pgmtx matrix="1,0,0,-1,0,654.525" page="37"/><pgmtx matrix="1,0,0,-1,0,654.525" page="38"/><pgmtx matrix="1,0,0,-1,0,654.525" page="39"/><pgmtx matrix="1,0,0,-1,0,654.525" page="40"/><pgmtx matrix="1,0,0,-1,0,654.525" page="41"/><pgmtx matrix="1,0,0,-1,0,654.525" page="42"/><pgmtx matrix="1,0,0,-1,0,654.525" page="43"/><pgmtx matrix="1,0,0,-1,0,654.525" page="44"/><pgmtx matrix="1,0,0,-1,0,654.525" page="45"/><pgmtx matrix="1,0,0,-1,0,654.525" page="46"/><pgmtx matrix="1,0,0,-1,0,654.525" page="47"/><pgmtx matrix="1,0,0,-1,0,654.525" page="48"/><pgmtx matrix="1,0,0,-1,0,654.525" page="49"/><pgmtx matrix="1,0,0,-1,0,654.525" page="50"/><pgmtx matrix="1,0,0,-1,0,654.525" page="51"/><pgmtx matrix="1,0,0,-1,0,654.525" page="52"/><pgmtx matrix="1,0,0,-1,0,654.525" page="53"/><pgmtx matrix="1,0,0,-1,0,654.525" page="54"/><pgmtx matrix="1,0,0,-1,0,654.525" page="55"/><pgmtx matrix="1,0,0,-1,0,654.525" page="56"/><pgmtx matrix="1,0,0,-1,0,654.525" page="57"/><pgmtx matrix="1,0,0,-1,0,654.525" page="58"/><pgmtx matrix="1,0,0,-1,0,654.525" page="59"/><pgmtx matrix="1,0,0,-1,0,654.525" page="60"/><pgmtx matrix="1,0,0,-1,0,654.525" page="61"/><pgmtx matrix="1,0,0,-1,0,654.525" page="62"/><pgmtx matrix="1,0,0,-1,0,654.525" page="63"/><pgmtx matrix="1,0,0,-1,0,654.525" page="64"/><pgmtx matrix="1,0,0,-1,0,654.525" page="65"/><pgmtx matrix="1,0,0,-1,0,654.525" page="66"/><pgmtx matrix="1,0,0,-1,0,654.525" page="67"/><pgmtx matrix="1,0,0,-1,0,654.525" page="68"/><pgmtx matrix="1,0,0,-1,0,654.525" page="69"/><pgmtx matrix="1,0,0,-1,0,654.525" page="70"/><pgmtx matrix="1,0,0,-1,0,654.525" page="71"/><pgmtx matrix="1,0,0,-1,0,654.525" page="72"/><pgmtx matrix="1,0,0,-1,0,654.525" page="73"/><pgmtx matrix="1,0,0,-1,0,654.525" page="74"/><pgmtx matrix="1,0,0,-1,0,654.525" page="75"/><pgmtx matrix="1,0,0,-1,0,654.525" page="76"/><pgmtx matrix="1,0,0,-1,0,654.525" page="77"/><pgmtx matrix="1,0,0,-1,0,654.525" page="78"/><pgmtx matrix="1,0,0,-1,0,654.525" page="79"/><pgmtx matrix="1,0,0,-1,0,654.525" page="80"/><pgmtx matrix="1,0,0,-1,0,654.525" page="81"/><pgmtx matrix="1,0,0,-1,0,654.525" page="82"/><pgmtx matrix="1,0,0,-1,0,654.525" page="83"/><pgmtx matrix="1,0,0,-1,0,654.525" page="84"/><pgmtx matrix="1,0,0,-1,0,654.525" page="85"/><pgmtx matrix="1,0,0,-1,0,654.525" page="86"/><pgmtx matrix="1,0,0,-1,0,654.525" page="87"/><pgmtx matrix="1,0,0,-1,0,654.525" page="88"/><pgmtx matrix="1,0,0,-1,0,654.525" page="89"/><pgmtx matrix="1,0,0,-1,0,654.525" page="90"/><pgmtx matrix="1,0,0,-1,0,654.525" page="91"/><pgmtx matrix="1,0,0,-1,0,654.525" page="92"/><pgmtx matrix="1,0,0,-1,0,654.525" page="93"/><pgmtx matrix="1,0,0,-1,0,654.525" page="94"/><pgmtx matrix="1,0,0,-1,0,654.525" page="95"/><pgmtx matrix="1,0,0,-1,0,654.525" page="96"/><pgmtx matrix="1,0,0,-1,0,654.525" page="97"/><pgmtx matrix="1,0,0,-1,0,654.525" page="98"/><pgmtx matrix="1,0,0,-1,0,654.525" page="99"/><pgmtx matrix="1,0,0,-1,0,654.525" page="100"/><pgmtx matrix="1,0,0,-1,0,654.525" page="101"/><pgmtx matrix="1,0,0,-1,0,654.525" page="102"/><pgmtx matrix="1,0,0,-1,0,654.525" page="103"/><pgmtx matrix="1,0,0,-1,0,654.525" page="104"/><pgmtx matrix="1,0,0,-1,0,654.525" page="105"/><pgmtx matrix="1,0,0,-1,0,654.525" page="106"/><pgmtx matrix="1,0,0,-1,0,654.525" page="107"/><pgmtx matrix="1,0,0,-1,0,654.525" page="108"/><pgmtx matrix="1,0,0,-1,0,654.525" page="109"/><pgmtx matrix="1,0,0,-1,0,654.525" page="110"/><pgmtx matrix="1,0,0,-1,0,654.525" page="111"/><pgmtx matrix="1,0,0,-1,0,654.525" page="112"/><pgmtx matrix="1,0,0,-1,0,654.525" page="113"/><pgmtx matrix="1,0,0,-1,0,654.525" page="114"/><pgmtx matrix="1,0,0,-1,0,654.525" page="115"/><pgmtx matrix="1,0,0,-1,0,654.525" page="116"/><pgmtx matrix="1,0,0,-1,0,654.525" page="117"/><pgmtx matrix="1,0,0,-1,0,654.525" page="118"/><pgmtx matrix="1,0,0,-1,0,654.525" page="119"/><pgmtx matrix="1,0,0,-1,0,654.525" page="120"/><pgmtx matrix="1,0,0,-1,0,654.525" page="121"/><pgmtx matrix="1,0,0,-1,0,654.525" page="122"/><pgmtx matrix="1,0,0,-1,0,654.525" page="123"/><pgmtx matrix="1,0,0,-1,0,654.525" page="124"/><pgmtx matrix="1,0,0,-1,0,654.525" page="125"/><pgmtx matrix="1,0,0,-1,0,654.525" page="126"/><pgmtx matrix="1,0,0,-1,0,654.525" page="127"/><pgmtx matrix="1,0,0,-1,0,654.525" page="128"/><pgmtx matrix="1,0,0,-1,0,654.525" page="129"/><pgmtx matrix="1,0,0,-1,0,654.525" page="130"/><pgmtx matrix="1,0,0,-1,0,654.525" page="131"/><pgmtx matrix="1,0,0,-1,0,654.525" page="132"/><pgmtx matrix="1,0,0,-1,0,654.525" page="133"/><pgmtx matrix="1,0,0,-1,0,654.525" page="134"/><pgmtx matrix="1,0,0,-1,0,654.525" page="135"/><pgmtx matrix="1,0,0,-1,0,654.525" page="136"/><pgmtx matrix="1,0,0,-1,0,654.525" page="137"/><pgmtx matrix="1,0,0,-1,0,654.525" page="138"/><pgmtx matrix="1,0,0,-1,0,654.525" page="139"/><pgmtx matrix="1,0,0,-1,0,654.525" page="140"/><pgmtx matrix="1,0,0,-1,0,654.525" page="141"/><pgmtx matrix="1,0,0,-1,0,654.525" page="142"/><pgmtx matrix="1,0,0,-1,0,654.525" page="143"/><pgmtx matrix="1,0,0,-1,0,654.525" page="144"/><pgmtx matrix="1,0,0,-1,0,654.525" page="145"/><pgmtx matrix="1,0,0,-1,0,654.525" page="146"/><pgmtx matrix="1,0,0,-1,0,654.525" page="147"/><pgmtx matrix="1,0,0,-1,0,654.525" page="148"/><pgmtx matrix="1,0,0,-1,0,654.525" page="149"/><pgmtx matrix="1,0,0,-1,0,654.525" page="150"/><pgmtx matrix="1,0,0,-1,0,654.525" page="151"/><pgmtx matrix="1,0,0,-1,0,654.525" page="152"/><pgmtx matrix="1,0,0,-1,0,654.525" page="153"/><pgmtx matrix="1,0,0,-1,0,654.525" page="154"/><pgmtx matrix="1,0,0,-1,0,654.525" page="155"/><pgmtx matrix="1,0,0,-1,0,654.525" page="156"/><pgmtx matrix="1,0,0,-1,0,654.525" page="157"/><pgmtx matrix="1,0,0,-1,0,654.525" page="158"/><pgmtx matrix="1,0,0,-1,0,654.525" page="159"/><pgmtx matrix="1,0,0,-1,0,654.525" page="160"/><pgmtx matrix="1,0,0,-1,0,654.525" page="161"/><pgmtx matrix="1,0,0,-1,0,654.525" page="162"/><pgmtx matrix="1,0,0,-1,0,654.525" page="163"/><pgmtx matrix="1,0,0,-1,0,654.525" page="164"/><pgmtx matrix="1,0,0,-1,0,654.525" page="165"/><pgmtx matrix="1,0,0,-1,0,654.525" page="166"/><pgmtx matrix="1,0,0,-1,0,654.525" page="167"/><pgmtx matrix="1,0,0,-1,0,654.525" page="168"/><pgmtx matrix="1,0,0,-1,0,654.525" page="169"/><pgmtx matrix="1,0,0,-1,0,654.525" page="170"/><pgmtx matrix="1,0,0,-1,0,654.525" page="171"/><pgmtx matrix="1,0,0,-1,0,654.525" page="172"/><pgmtx matrix="1,0,0,-1,0,654.525" page="173"/><pgmtx matrix="1,0,0,-1,0,654.525" page="174"/><pgmtx matrix="1,0,0,-1,0,654.525" page="175"/><pgmtx matrix="1,0,0,-1,0,654.525" page="176"/><pgmtx matrix="1,0,0,-1,0,654.525" page="177"/><pgmtx matrix="1,0,0,-1,0,654.525" page="178"/><pgmtx matrix="1,0,0,-1,0,654.525" page="179"/><pgmtx matrix="1,0,0,-1,0,654.525" page="180"/><pgmtx matrix="1,0,0,-1,0,654.525" page="181"/><pgmtx matrix="1,0,0,-1,0,654.525" page="182"/><pgmtx matrix="1,0,0,-1,0,654.525" page="183"/><pgmtx matrix="1,0,0,-1,0,654.525" page="184"/><pgmtx matrix="1,0,0,-1,0,654.525" page="185"/><pgmtx matrix="1,0,0,-1,0,654.525" page="186"/><pgmtx matrix="1,0,0,-1,0,654.525" page="187"/><pgmtx matrix="1,0,0,-1,0,654.525" page="188"/><pgmtx matrix="1,0,0,-1,0,654.525" page="189"/><pgmtx matrix="1,0,0,-1,0,654.525" page="190"/><pgmtx matrix="1,0,0,-1,0,654.525" page="191"/><pgmtx matrix="1,0,0,-1,0,654.525" page="192"/><pgmtx matrix="1,0,0,-1,0,654.525" page="193"/><pgmtx matrix="1,0,0,-1,0,654.525" page="194"/><pgmtx matrix="1,0,0,-1,0,654.525" page="195"/><pgmtx matrix="1,0,0,-1,0,654.525" page="196"/><pgmtx matrix="1,0,0,-1,0,654.525" page="197"/><pgmtx matrix="1,0,0,-1,0,654.525" page="198"/><pgmtx matrix="1,0,0,-1,0,654.525" page="199"/><pgmtx matrix="1,0,0,-1,0,654.525" page="200"/><pgmtx matrix="1,0,0,-1,0,654.525" page="201"/><pgmtx matrix="1,0,0,-1,0,654.525" page="202"/><pgmtx matrix="1,0,0,-1,0,654.525" page="203"/><pgmtx matrix="1,0,0,-1,0,654.525" page="204"/><pgmtx matrix="1,0,0,-1,0,654.525" page="205"/><pgmtx matrix="1,0,0,-1,0,654.525" page="206"/><pgmtx matrix="1,0,0,-1,0,654.525" page="207"/><pgmtx matrix="1,0,0,-1,0,654.525" page="208"/><pgmtx matrix="1,0,0,-1,0,654.525" page="209"/><pgmtx matrix="1,0,0,-1,0,654.525" page="210"/><pgmtx matrix="1,0,0,-1,0,654.525" page="211"/><pgmtx matrix="1,0,0,-1,0,654.525" page="212"/><pgmtx matrix="1,0,0,-1,0,654.525" page="213"/><pgmtx matrix="1,0,0,-1,0,654.525" page="214"/><pgmtx matrix="1,0,0,-1,0,654.525" page="215"/><pgmtx matrix="1,0,0,-1,0,654.525" page="216"/><pgmtx matrix="1,0,0,-1,0,654.525" page="217"/><pgmtx matrix="1,0,0,-1,0,654.525" page="218"/><pgmtx matrix="1,0,0,-1,0,654.525" page="219"/><pgmtx matrix="1,0,0,-1,0,654.525" page="220"/><pgmtx matrix="1,0,0,-1,0,654.525" page="221"/><pgmtx matrix="1,0,0,-1,0,654.525" page="222"/><pgmtx matrix="1,0,0,-1,0,654.525" page="223"/><pgmtx matrix="1,0,0,-1,0,654.525" page="224"/><pgmtx matrix="1,0,0,-1,0,654.525" page="225"/><pgmtx matrix="1,0,0,-1,0,654.525" page="226"/><pgmtx matrix="1,0,0,-1,0,654.525" page="227"/><pgmtx matrix="1,0,0,-1,0,654.525" page="228"/><pgmtx matrix="1,0,0,-1,0,654.525" page="229"/><pgmtx matrix="1,0,0,-1,0,654.525" page="230"/><pgmtx matrix="1,0,0,-1,0,654.525" page="231"/><pgmtx matrix="1,0,0,-1,0,654.525" page="232"/><pgmtx matrix="1,0,0,-1,0,654.525" page="233"/><pgmtx matrix="1,0,0,-1,0,654.525" page="234"/><pgmtx matrix="1,0,0,-1,0,654.525" page="235"/><pgmtx matrix="1,0,0,-1,0,654.525" page="236"/><pgmtx matrix="1,0,0,-1,0,654.525" page="237"/><pgmtx matrix="1,0,0,-1,0,654.525" page="238"/><pgmtx matrix="1,0,0,-1,0,654.525" page="239"/><pgmtx matrix="1,0,0,-1,0,654.525" page="240"/><pgmtx matrix="1,0,0,-1,0,654.525" page="241"/><pgmtx matrix="1,0,0,-1,0,654.525" page="242"/><pgmtx matrix="1,0,0,-1,0,654.525" page="243"/><pgmtx matrix="1,0,0,-1,0,654.525" page="244"/><pgmtx matrix="1,0,0,-1,0,654.525" page="245"/><pgmtx matrix="1,0,0,-1,0,654.525" page="246"/><pgmtx matrix="1,0,0,-1,0,654.525" page="247"/><pgmtx matrix="1,0,0,-1,0,654.525" page="248"/><pgmtx matrix="1,0,0,-1,0,654.525" page="249"/><pgmtx matrix="1,0,0,-1,0,654.525" page="250"/><pgmtx matrix="1,0,0,-1,0,654.525" page="251"/><pgmtx matrix="1,0,0,-1,0,654.525" page="252"/><pgmtx matrix="1,0,0,-1,0,654.525" page="253"/><pgmtx matrix="1,0,0,-1,0,654.525" page="254"/><pgmtx matrix="1,0,0,-1,0,654.525" page="255"/><pgmtx matrix="1,0,0,-1,0,654.525" page="256"/><pgmtx matrix="1,0,0,-1,0,654.525" page="257"/><pgmtx matrix="1,0,0,-1,0,654.525" page="258"/><pgmtx matrix="1,0,0,-1,0,654.525" page="259"/><pgmtx matrix="1,0,0,-1,0,654.525" page="260"/><pgmtx matrix="1,0,0,-1,0,654.525" page="261"/><pgmtx matrix="1,0,0,-1,0,654.525" page="262"/><pgmtx matrix="1,0,0,-1,0,654.525" page="263"/><pgmtx matrix="1,0,0,-1,0,654.525" page="264"/><pgmtx matrix="1,0,0,-1,0,654.525" page="265"/><pgmtx matrix="1,0,0,-1,0,654.525" page="266"/><pgmtx matrix="1,0,0,-1,0,654.525" page="267"/><pgmtx matrix="1,0,0,-1,0,654.525" page="268"/><pgmtx matrix="1,0,0,-1,0,654.525" page="269"/><pgmtx matrix="1,0,0,-1,0,654.525" page="270"/><pgmtx matrix="1,0,0,-1,0,654.525" page="271"/><pgmtx matrix="1,0,0,-1,0,654.525" page="272"/><pgmtx matrix="1,0,0,-1,0,654.525" page="273"/><pgmtx matrix="1,0,0,-1,0,654.525" page="274"/><pgmtx matrix="1,0,0,-1,0,654.525" page="275"/><pgmtx matrix="1,0,0,-1,0,654.525" page="276"/><pgmtx matrix="1,0,0,-1,0,654.525" page="277"/><pgmtx matrix="1,0,0,-1,0,654.525" page="278"/><pgmtx matrix="1,0,0,-1,0,654.525" page="279"/><pgmtx matrix="1,0,0,-1,0,654.525" page="280"/><pgmtx matrix="1,0,0,-1,0,654.525" page="281"/><pgmtx matrix="1,0,0,-1,0,654.525" page="282"/><pgmtx matrix="1,0,0,-1,0,654.525" page="283"/><pgmtx matrix="1,0,0,-1,0,654.525" page="284"/><pgmtx matrix="1,0,0,-1,0,654.525" page="285"/><pgmtx matrix="1,0,0,-1,0,654.525" page="286"/><pgmtx matrix="1,0,0,-1,0,654.525" page="287"/><pgmtx matrix="1,0,0,-1,0,654.525" page="288"/><pgmtx matrix="1,0,0,-1,0,654.525" page="289"/><pgmtx matrix="1,0,0,-1,0,654.525" page="290"/><pgmtx matrix="1,0,0,-1,0,654.525" page="291"/><pgmtx matrix="1,0,0,-1,0,654.525" page="292"/><pgmtx matrix="1,0,0,-1,0,654.525" page="293"/><pgmtx matrix="1,0,0,-1,0,654.525" page="294"/><pgmtx matrix="1,0,0,-1,0,654.525" page="295"/><pgmtx matrix="1,0,0,-1,0,654.525" page="296"/><pgmtx matrix="1,0,0,-1,0,654.525" page="297"/><pgmtx matrix="1,0,0,-1,0,654.525" page="298"/><pgmtx matrix="1,0,0,-1,0,654.525" page="299"/><pgmtx matrix="1,0,0,-1,0,654.525" page="300"/><pgmtx matrix="1,0,0,-1,0,654.525" page="301"/><pgmtx matrix="1,0,0,-1,0,654.525" page="302"/><pgmtx matrix="1,0,0,-1,0,654.525" page="303"/><pgmtx matrix="1,0,0,-1,0,654.525" page="304"/><pgmtx matrix="1,0,0,-1,0,654.525" page="305"/><pgmtx matrix="1,0,0,-1,0,654.525" page="306"/><pgmtx matrix="1,0,0,-1,0,654.525" page="307"/><pgmtx matrix="1,0,0,-1,0,654.525" page="308"/><pgmtx matrix="1,0,0,-1,0,654.525" page="309"/><pgmtx matrix="1,0,0,-1,0,654.525" page="310"/><pgmtx matrix="1,0,0,-1,0,654.525" page="311"/><pgmtx matrix="1,0,0,-1,0,654.525" page="312"/><pgmtx matrix="1,0,0,-1,0,654.525" page="313"/><pgmtx matrix="1,0,0,-1,0,654.525" page="314"/><pgmtx matrix="1,0,0,-1,0,654.525" page="315"/><pgmtx matrix="1,0,0,-1,0,654.525" page="316"/><pgmtx matrix="1,0,0,-1,0,654.525" page="317"/><pgmtx matrix="1,0,0,-1,0,654.525" page="318"/><pgmtx matrix="1,0,0,-1,0,654.525" page="319"/><pgmtx matrix="1,0,0,-1,0,654.525" page="320"/><pgmtx matrix="1,0,0,-1,0,654.525" page="321"/><pgmtx matrix="1,0,0,-1,0,654.525" page="322"/><pgmtx matrix="1,0,0,-1,0,654.525" page="323"/><pgmtx matrix="1,0,0,-1,0,654.525" page="324"/><pgmtx matrix="1,0,0,-1,0,654.525" page="325"/><pgmtx matrix="1,0,0,-1,0,654.525" page="326"/><pgmtx matrix="1,0,0,-1,0,654.525" page="327"/><pgmtx matrix="1,0,0,-1,0,654.525" page="328"/><pgmtx matrix="1,0,0,-1,0,654.525" page="329"/><pgmtx matrix="1,0,0,-1,0,654.525" page="330"/><pgmtx matrix="1,0,0,-1,0,654.525" page="331"/><pgmtx matrix="1,0,0,-1,0,654.525" page="332"/><pgmtx matrix="1,0,0,-1,0,654.525" page="333"/><pgmtx matrix="1,0,0,-1,0,654.525" page="334"/><pgmtx matrix="1,0,0,-1,0,654.525" page="335"/><pgmtx matrix="1,0,0,-1,0,654.525" page="336"/><pgmtx matrix="1,0,0,-1,0,654.525" page="337"/><pgmtx matrix="1,0,0,-1,0,654.525" page="338"/><pgmtx matrix="1,0,0,-1,0,654.525" page="339"/><pgmtx matrix="1,0,0,-1,0,654.525" page="340"/><pgmtx matrix="1,0,0,-1,0,654.525" page="341"/><pgmtx matrix="1,0,0,-1,0,654.525" page="342"/><pgmtx matrix="1,0,0,-1,0,654.525" page="343"/><pgmtx matrix="1,0,0,-1,0,654.525" page="344"/><pgmtx matrix="1,0,0,-1,0,654.525" page="345"/><pgmtx matrix="1,0,0,-1,0,654.525" page="346"/><pgmtx matrix="1,0,0,-1,0,654.525" page="347"/><pgmtx matrix="1,0,0,-1,0,654.525" page="348"/><pgmtx matrix="1,0,0,-1,0,654.525" page="349"/><pgmtx matrix="1,0,0,-1,0,654.525" page="350"/><pgmtx matrix="1,0,0,-1,0,654.525" page="351"/><pgmtx matrix="1,0,0,-1,0,654.525" page="352"/><pgmtx matrix="1,0,0,-1,0,654.525" page="353"/><pgmtx matrix="1,0,0,-1,0,654.525" page="354"/><pgmtx matrix="1,0,0,-1,0,654.525" page="355"/><pgmtx matrix="1,0,0,-1,0,654.525" page="356"/><pgmtx matrix="1,0,0,-1,0,654.525" page="357"/><pgmtx matrix="1,0,0,-1,0,654.525" page="358"/><pgmtx matrix="1,0,0,-1,0,654.525" page="359"/><pgmtx matrix="1,0,0,-1,0,654.525" page="360"/><pgmtx matrix="1,0,0,-1,0,654.525" page="361"/><pgmtx matrix="1,0,0,-1,0,654.525" page="362"/><pgmtx matrix="1,0,0,-1,0,654.525" page="363"/><pgmtx matrix="1,0,0,-1,0,654.525" page="364"/><pgmtx matrix="1,0,0,-1,0,654.525" page="365"/><pgmtx matrix="1,0,0,-1,0,654.525" page="366"/><pgmtx matrix="1,0,0,-1,0,654.525" page="367"/><pgmtx matrix="1,0,0,-1,0,654.525" page="368"/><pgmtx matrix="1,0,0,-1,0,654.525" page="369"/><pgmtx matrix="1,0,0,-1,0,654.525" page="370"/><pgmtx matrix="1,0,0,-1,0,654.525" page="371"/><pgmtx matrix="1,0,0,-1,0,654.525" page="372"/><pgmtx matrix="1,0,0,-1,0,654.525" page="373"/><pgmtx matrix="1,0,0,-1,0,654.525" page="374"/><pgmtx matrix="1,0,0,-1,0,654.525" page="375"/><pgmtx matrix="1,0,0,-1,0,654.525" page="376"/><pgmtx matrix="1,0,0,-1,0,654.525" page="377"/><pgmtx matrix="1,0,0,-1,0,654.525" page="378"/><pgmtx matrix="1,0,0,-1,0,654.525" page="379"/><pgmtx matrix="1,0,0,-1,0,654.525" page="380"/><pgmtx matrix="1,0,0,-1,0,654.525" page="381"/><pgmtx matrix="1,0,0,-1,0,654.525" page="382"/><pgmtx matrix="1,0,0,-1,0,654.525" page="383"/><pgmtx matrix="1,0,0,-1,0,654.525" page="384"/><pgmtx matrix="1,0,0,-1,0,654.525" page="385"/><pgmtx matrix="1,0,0,-1,0,654.525" page="386"/><pgmtx matrix="1,0,0,-1,0,654.525" page="387"/><pgmtx matrix="1,0,0,-1,0,654.525" page="388"/><pgmtx matrix="1,0,0,-1,0,654.525" page="389"/><pgmtx matrix="1,0,0,-1,0,654.525" page="390"/><pgmtx matrix="1,0,0,-1,0,654.525" page="391"/><pgmtx matrix="1,0,0,-1,0,654.525" page="392"/><pgmtx matrix="1,0,0,-1,0,654.525" page="393"/><pgmtx matrix="1,0,0,-1,0,654.525" page="394"/><pgmtx matrix="1,0,0,-1,0,654.525" page="395"/><pgmtx matrix="1,0,0,-1,0,654.525" page="396"/><pgmtx matrix="1,0,0,-1,0,654.525" page="397"/><pgmtx matrix="1,0,0,-1,0,654.525" page="398"/><pgmtx matrix="1,0,0,-1,0,654.525" page="399"/><pgmtx matrix="1,0,0,-1,0,654.525" page="400"/><pgmtx matrix="1,0,0,-1,0,654.525" page="401"/><pgmtx matrix="1,0,0,-1,0,654.525" page="402"/><pgmtx matrix="1,0,0,-1,0,654.525" page="403"/><pgmtx matrix="1,0,0,-1,0,654.525" page="404"/><pgmtx matrix="1,0,0,-1,0,654.525" page="405"/><pgmtx matrix="1,0,0,-1,0,654.525" page="406"/><pgmtx matrix="1,0,0,-1,0,654.525" page="407"/><pgmtx matrix="1,0,0,-1,0,654.525" page="408"/><pgmtx matrix="1,0,0,-1,0,654.525" page="409"/><pgmtx matrix="1,0,0,-1,0,654.525" page="410"/><pgmtx matrix="1,0,0,-1,0,654.525" page="411"/><pgmtx matrix="1,0,0,-1,0,654.525" page="412"/><pgmtx matrix="1,0,0,-1,0,654.525" page="413"/><pgmtx matrix="1,0,0,-1,0,654.525" page="414"/><pgmtx matrix="1,0,0,-1,0,654.525" page="415"/><pgmtx matrix="1,0,0,-1,0,654.525" page="416"/><pgmtx matrix="1,0,0,-1,0,654.525" page="417"/><pgmtx matrix="1,0,0,-1,0,654.525" page="418"/><pgmtx matrix="1,0,0,-1,0,654.525" page="419"/><pgmtx matrix="1,0,0,-1,0,654.525" page="420"/><pgmtx matrix="1,0,0,-1,0,654.525" page="421"/><pgmtx matrix="1,0,0,-1,0,654.525" page="422"/><pgmtx matrix="1,0,0,-1,0,654.525" page="423"/><pgmtx matrix="1,0,0,-1,0,654.525" page="424"/><pgmtx matrix="1,0,0,-1,0,654.525" page="425"/><pgmtx matrix="1,0,0,-1,0,654.525" page="426"/><pgmtx matrix="1,0,0,-1,0,654.525" page="427"/><pgmtx matrix="1,0,0,-1,0,654.525" page="428"/><pgmtx matrix="1,0,0,-1,0,654.525" page="429"/><pgmtx matrix="1,0,0,-1,0,654.525" page="430"/><pgmtx matrix="1,0,0,-1,0,654.525" page="431"/><pgmtx matrix="1,0,0,-1,0,654.525" page="432"/><pgmtx matrix="1,0,0,-1,0,654.525" page="433"/><pgmtx matrix="1,0,0,-1,0,654.525" page="434"/><pgmtx matrix="1,0,0,-1,0,654.525" page="435"/><pgmtx matrix="1,0,0,-1,0,654.525" page="436"/><pgmtx matrix="1,0,0,-1,0,654.525" page="437"/><pgmtx matrix="1,0,0,-1,0,654.525" page="438"/><pgmtx matrix="1,0,0,-1,0,654.525" page="439"/><pgmtx matrix="1,0,0,-1,0,654.525" page="440"/><pgmtx matrix="1,0,0,-1,0,654.525" page="441"/><pgmtx matrix="1,0,0,-1,0,654.525" page="442"/><pgmtx matrix="1,0,0,-1,0,654.525" page="443"/><pgmtx matrix="1,0,0,-1,0,654.525" page="444"/><pgmtx matrix="1,0,0,-1,0,654.525" page="445"/><pgmtx matrix="1,0,0,-1,0,654.525" page="446"/><pgmtx matrix="1,0,0,-1,0,654.525" page="447"/><pgmtx matrix="1,0,0,-1,0,654.525" page="448"/><pgmtx matrix="1,0,0,-1,0,654.525" page="449"/><pgmtx matrix="1,0,0,-1,0,654.525" page="450"/><pgmtx matrix="1,0,0,-1,0,654.525" page="451"/><pgmtx matrix="1,0,0,-1,0,654.525" page="452"/><pgmtx matrix="1,0,0,-1,0,654.525" page="453"/><pgmtx matrix="1,0,0,-1,0,654.525" page="454"/><pgmtx matrix="1,0,0,-1,0,654.525" page="455"/><pgmtx matrix="1,0,0,-1,0,654.525" page="456"/><pgmtx matrix="1,0,0,-1,0,654.525" page="457"/><pgmtx matrix="1,0,0,-1,0,654.525" page="458"/><pgmtx matrix="1,0,0,-1,0,654.525" page="459"/><pgmtx matrix="1,0,0,-1,0,654.525" page="460"/><pgmtx matrix="1,0,0,-1,0,654.525" page="461"/><pgmtx matrix="1,0,0,-1,0,654.525" page="462"/><pgmtx matrix="1,0,0,-1,0,654.525" page="463"/><pgmtx matrix="1,0,0,-1,0,654.525" page="464"/><pgmtx matrix="1,0,0,-1,0,654.525" page="465"/><pgmtx matrix="1,0,0,-1,0,654.525" page="466"/><pgmtx matrix="1,0,0,-1,0,654.525" page="467"/><pgmtx matrix="1,0,0,-1,0,654.525" page="468"/><pgmtx matrix="1,0,0,-1,0,654.525" page="469"/><pgmtx matrix="1,0,0,-1,0,654.525" page="470"/><pgmtx matrix="1,0,0,-1,0,654.525" page="471"/><pgmtx matrix="1,0,0,-1,0,654.525" page="472"/><pgmtx matrix="1,0,0,-1,0,654.525" page="473"/><pgmtx matrix="1,0,0,-1,0,654.525" page="474"/><pgmtx matrix="1,0,0,-1,0,654.525" page="475"/><pgmtx matrix="1,0,0,-1,0,654.525" page="476"/><pgmtx matrix="1,0,0,-1,0,654.525" page="477"/><pgmtx matrix="1,0,0,-1,0,654.525" page="478"/><pgmtx matrix="1,0,0,-1,0,654.525" page="479"/><pgmtx matrix="1,0,0,-1,0,654.525" page="480"/><pgmtx matrix="1,0,0,-1,0,654.525" page="481"/><pgmtx matrix="1,0,0,-1,0,654.525" page="482"/><pgmtx matrix="1,0,0,-1,0,654.525" page="483"/><pgmtx matrix="1,0,0,-1,0,654.525" page="484"/><pgmtx matrix="1,0,0,-1,0,654.525" page="485"/><pgmtx matrix="1,0,0,-1,0,654.525" page="486"/><pgmtx matrix="1,0,0,-1,0,654.525" page="487"/><pgmtx matrix="1,0,0,-1,0,654.525" page="488"/><pgmtx matrix="1,0,0,-1,0,654.525" page="489"/><pgmtx matrix="1,0,0,-1,0,654.525" page="490"/><pgmtx matrix="1,0,0,-1,0,654.525" page="491"/><pgmtx matrix="1,0,0,-1,0,654.525" page="492"/><pgmtx matrix="1,0,0,-1,0,654.525" page="493"/><pgmtx matrix="1,0,0,-1,0,654.525" page="494"/><pgmtx matrix="1,0,0,-1,0,654.525" page="495"/><pgmtx matrix="1,0,0,-1,0,654.525" page="496"/><pgmtx matrix="1,0,0,-1,0,654.525" page="497"/><pgmtx matrix="1,0,0,-1,0,654.525" page="498"/><pgmtx matrix="1,0,0,-1,0,654.525" page="499"/><pgmtx matrix="1,0,0,-1,0,654.525" page="500"/><pgmtx matrix="1,0,0,-1,0,654.525" page="501"/><pgmtx matrix="1,0,0,-1,0,654.525" page="502"/><pgmtx matrix="1,0,0,-1,0,654.525" page="503"/><pgmtx matrix="1,0,0,-1,0,654.525" page="504"/><pgmtx matrix="1,0,0,-1,0,654.525" page="505"/><pgmtx matrix="1,0,0,-1,0,654.525" page="506"/><pgmtx matrix="1,0,0,-1,0,654.525" page="507"/><pgmtx matrix="1,0,0,-1,0,654.525" page="508"/><pgmtx matrix="1,0,0,-1,0,654.525" page="509"/><pgmtx matrix="1,0,0,-1,0,654.525" page="510"/><pgmtx matrix="1,0,0,-1,0,654.525" page="511"/><pgmtx matrix="1,0,0,-1,0,654.525" page="512"/><pgmtx matrix="1,0,0,-1,0,654.525" page="513"/><pgmtx matrix="1,0,0,-1,0,654.525" page="514"/><pgmtx matrix="1,0,0,-1,0,654.525" page="515"/><pgmtx matrix="1,0,0,-1,0,654.525" page="516"/><pgmtx matrix="1,0,0,-1,0,654.525" page="517"/><pgmtx matrix="1,0,0,-1,0,654.525" page="518"/><pgmtx matrix="1,0,0,-1,0,654.525" page="519"/><pgmtx matrix="1,0,0,-1,0,654.525" page="520"/><pgmtx matrix="1,0,0,-1,0,654.525" page="521"/><pgmtx matrix="1,0,0,-1,0,654.525" page="522"/><pgmtx matrix="1,0,0,-1,0,654.525" page="523"/><pgmtx matrix="1,0,0,-1,0,654.525" page="524"/><pgmtx matrix="1,0,0,-1,0,654.525" page="525"/><pgmtx matrix="1,0,0,-1,0,654.525" page="526"/><pgmtx matrix="1,0,0,-1,0,654.525" page="527"/><pgmtx matrix="1,0,0,-1,0,654.525" page="528"/><pgmtx matrix="1,0,0,-1,0,654.525" page="529"/><pgmtx matrix="1,0,0,-1,0,654.525" page="530"/><pgmtx matrix="1,0,0,-1,0,654.525" page="531"/><pgmtx matrix="1,0,0,-1,0,654.525" page="532"/><pgmtx matrix="1,0,0,-1,0,654.525" page="533"/><pgmtx matrix="1,0,0,-1,0,654.525" page="534"/><pgmtx matrix="1,0,0,-1,0,654.525" page="535"/><pgmtx matrix="1,0,0,-1,0,654.525" page="536"/><pgmtx matrix="1,0,0,-1,0,654.525" page="537"/><pgmtx matrix="1,0,0,-1,0,654.525" page="538"/><pgmtx matrix="1,0,0,-1,0,654.525" page="539"/><pgmtx matrix="1,0,0,-1,0,654.525" page="540"/><pgmtx matrix="1,0,0,-1,0,654.525" page="541"/><pgmtx matrix="1,0,0,-1,0,654.525" page="542"/><pgmtx matrix="1,0,0,-1,0,654.525" page="543"/><pgmtx matrix="1,0,0,-1,0,654.525" page="544"/><pgmtx matrix="1,0,0,-1,0,654.525" page="545"/><pgmtx matrix="1,0,0,-1,0,654.525" page="546"/><pgmtx matrix="1,0,0,-1,0,654.525" page="547"/><pgmtx matrix="1,0,0,-1,0,654.525" page="548"/><pgmtx matrix="1,0,0,-1,0,654.525" page="549"/><pgmtx matrix="1,0,0,-1,0,654.525" page="550"/><pgmtx matrix="1,0,0,-1,0,654.525" page="551"/><pgmtx matrix="1,0,0,-1,0,654.525" page="552"/><pgmtx matrix="1,0,0,-1,0,654.525" page="553"/><pgmtx matrix="1,0,0,-1,0,654.525" page="554"/><pgmtx matrix="1,0,0,-1,0,654.525" page="555"/><pgmtx matrix="1,0,0,-1,0,654.525" page="556"/><pgmtx matrix="1,0,0,-1,0,654.525" page="557"/><pgmtx matrix="1,0,0,-1,0,654.525" page="558"/><pgmtx matrix="1,0,0,-1,0,654.525" page="559"/><pgmtx matrix="1,0,0,-1,0,654.525" page="560"/><pgmtx matrix="1,0,0,-1,0,654.525" page="561"/><pgmtx matrix="1,0,0,-1,0,654.525" page="562"/><pgmtx matrix="1,0,0,-1,0,654.525" page="563"/><pgmtx matrix="1,0,0,-1,0,654.525" page="564"/><pgmtx matrix="1,0,0,-1,0,654.525" page="565"/><pgmtx matrix="1,0,0,-1,0,654.525" page="566"/><pgmtx matrix="1,0,0,-1,0,654.525" page="567"/><pgmtx matrix="1,0,0,-1,0,654.525" page="568"/><pgmtx matrix="1,0,0,-1,0,654.525" page="569"/><pgmtx matrix="1,0,0,-1,0,654.525" page="570"/><pgmtx matrix="1,0,0,-1,0,654.525" page="571"/><pgmtx matrix="1,0,0,-1,0,654.525" page="572"/><pgmtx matrix="1,0,0,-1,0,654.525" page="573"/><pgmtx matrix="1,0,0,-1,0,654.525" page="574"/><pgmtx matrix="1,0,0,-1,0,654.525" page="575"/><pgmtx matrix="1,0,0,-1,0,654.525" page="576"/><pgmtx matrix="1,0,0,-1,0,654.525" page="577"/><pgmtx matrix="1,0,0,-1,0,654.525" page="578"/><pgmtx matrix="1,0,0,-1,0,654.525" page="579"/><pgmtx matrix="1,0,0,-1,0,654.525" page="580"/><pgmtx matrix="1,0,0,-1,0,654.525" page="581"/><pgmtx matrix="1,0,0,-1,0,654.525" page="582"/><pgmtx matrix="1,0,0,-1,0,654.525" page="583"/><pgmtx matrix="1,0,0,-1,0,654.525" page="584"/><pgmtx matrix="1,0,0,-1,0,654.525" page="585"/><pgmtx matrix="1,0,0,-1,0,654.525" page="586"/><pgmtx matrix="1,0,0,-1,0,654.525" page="587"/><pgmtx matrix="1,0,0,-1,0,654.525" page="588"/><pgmtx matrix="1,0,0,-1,0,654.525" page="589"/><pgmtx matrix="1,0,0,-1,0,654.525" page="590"/><pgmtx matrix="1,0,0,-1,0,654.525" page="591"/><pgmtx matrix="1,0,0,-1,0,654.525" page="592"/><pgmtx matrix="1,0,0,-1,0,654.525" page="593"/><pgmtx matrix="1,0,0,-1,0,654.525" page="594"/><pgmtx matrix="1,0,0,-1,0,654.525" page="595"/><pgmtx matrix="1,0,0,-1,0,654.525" page="596"/><pgmtx matrix="1,0,0,-1,0,654.525" page="597"/><pgmtx matrix="1,0,0,-1,0,654.525" page="598"/><pgmtx matrix="1,0,0,-1,0,654.525" page="599"/><pgmtx matrix="1,0,0,-1,0,654.525" page="600"/><pgmtx matrix="1,0,0,-1,0,654.525" page="601"/><pgmtx matrix="1,0,0,-1,0,654.525" page="602"/><pgmtx matrix="1,0,0,-1,0,654.525" page="603"/><pgmtx matrix="1,0,0,-1,0,654.525" page="604"/><pgmtx matrix="1,0,0,-1,0,654.525" page="605"/><pgmtx matrix="1,0,0,-1,0,654.525" page="606"/><pgmtx matrix="1,0,0,-1,0,654.525" page="607"/><pgmtx matrix="1,0,0,-1,0,654.525" page="608"/><pgmtx matrix="1,0,0,-1,0,654.525" page="609"/><pgmtx matrix="1,0,0,-1,0,654.525" page="610"/><pgmtx matrix="1,0,0,-1,0,654.525" page="611"/><pgmtx matrix="1,0,0,-1,0,654.525" page="612"/><pgmtx matrix="1,0,0,-1,0,654.525" page="613"/><pgmtx matrix="1,0,0,-1,0,654.525" page="614"/><pgmtx matrix="1,0,0,-1,0,654.525" page="615"/><pgmtx matrix="1,0,0,-1,0,654.525" page="616"/><pgmtx matrix="1,0,0,-1,0,654.525" page="617"/><pgmtx matrix="1,0,0,-1,0,654.525" page="618"/><pgmtx matrix="1,0,0,-1,0,654.525" page="619"/><pgmtx matrix="1,0,0,-1,0,654.525" page="620"/><pgmtx matrix="1,0,0,-1,0,654.525" page="621"/><pgmtx matrix="1,0,0,-1,0,654.525" page="622"/><pgmtx matrix="1,0,0,-1,0,654.525" page="623"/><pgmtx matrix="1,0,0,-1,0,654.525" page="624"/><pgmtx matrix="1,0,0,-1,0,654.525" page="625"/><pgmtx matrix="1,0,0,-1,0,654.525" page="626"/><pgmtx matrix="1,0,0,-1,0,654.525" page="627"/><pgmtx matrix="1,0,0,-1,0,654.525" page="628"/><pgmtx matrix="1,0,0,-1,0,654.525" page="629"/><pgmtx matrix="1,0,0,-1,0,654.525" page="630"/><pgmtx matrix="1,0,0,-1,0,654.525" page="631"/><pgmtx matrix="1,0,0,-1,0,654.525" page="632"/><pgmtx matrix="1,0,0,-1,0,654.525" page="633"/><pgmtx matrix="1,0,0,-1,0,654.525" page="634"/><pgmtx matrix="1,0,0,-1,0,654.525" page="635"/><pgmtx matrix="1,0,0,-1,0,654.525" page="636"/><pgmtx matrix="1,0,0,-1,0,654.525" page="637"/><pgmtx matrix="1,0,0,-1,0,654.525" page="638"/><pgmtx matrix="1,0,0,-1,0,654.525" page="639"/><pgmtx matrix="1,0,0,-1,0,654.525" page="640"/><pgmtx matrix="1,0,0,-1,0,654.525" page="641"/><pgmtx matrix="1,0,0,-1,0,654.525" page="642"/><pgmtx matrix="1,0,0,-1,0,654.525" page="643"/><pgmtx matrix="1,0,0,-1,0,654.525" page="644"/><pgmtx matrix="1,0,0,-1,0,654.525" page="645"/><pgmtx matrix="1,0,0,-1,0,654.525" page="646"/><pgmtx matrix="1,0,0,-1,0,654.525" page="647"/><pgmtx matrix="1,0,0,-1,0,654.525" page="648"/><pgmtx matrix="1,0,0,-1,0,654.525" page="649"/><pgmtx matrix="1,0,0,-1,0,654.525" page="650"/><pgmtx matrix="1,0,0,-1,0,654.525" page="651"/><pgmtx matrix="1,0,0,-1,0,654.525" page="652"/><pgmtx matrix="1,0,0,-1,0,654.525" page="653"/><pgmtx matrix="1,0,0,-1,0,654.525" page="654"/><pgmtx matrix="1,0,0,-1,0,654.525" page="655"/><pgmtx matrix="1,0,0,-1,0,654.525" page="656"/><pgmtx matrix="1,0,0,-1,0,654.525" page="657"/><pgmtx matrix="1,0,0,-1,0,654.525" page="658"/><pgmtx matrix="1,0,0,-1,0,654.525" page="659"/><pgmtx matrix="1,0,0,-1,0,654.525" page="660"/><pgmtx matrix="1,0,0,-1,0,654.525" page="661"/><pgmtx matrix="1,0,0,-1,0,654.525" page="662"/><pgmtx matrix="1,0,0,-1,0,654.525" page="663"/><pgmtx matrix="1,0,0,-1,0,654.525" page="664"/><pgmtx matrix="1,0,0,-1,0,654.525" page="665"/><pgmtx matrix="1,0,0,-1,0,654.525" page="666"/><pgmtx matrix="1,0,0,-1,0,654.525" page="667"/><pgmtx matrix="1,0,0,-1,0,654.525" page="668"/><pgmtx matrix="1,0,0,-1,0,654.525" page="669"/><pgmtx matrix="1,0,0,-1,0,654.525" page="670"/><pgmtx matrix="1,0,0,-1,0,654.525" page="671"/><pgmtx matrix="1,0,0,-1,0,654.525" page="672"/><pgmtx matrix="1,0,0,-1,0,654.525" page="673"/><pgmtx matrix="1,0,0,-1,0,654.525" page="674"/><pgmtx matrix="1,0,0,-1,0,654.525" page="675"/><pgmtx matrix="1,0,0,-1,0,654.525" page="676"/><pgmtx matrix="1,0,0,-1,0,654.525" page="677"/><pgmtx matrix="1,0,0,-1,0,654.525" page="678"/><pgmtx matrix="1,0,0,-1,0,654.525" page="679"/><pgmtx matrix="1,0,0,-1,0,654.525" page="680"/><pgmtx matrix="1,0,0,-1,0,654.525" page="681"/><pgmtx matrix="1,0,0,-1,0,654.525" page="682"/><pgmtx matrix="1,0,0,-1,0,654.525" page="683"/><pgmtx matrix="1,0,0,-1,0,654.525" page="684"/><pgmtx matrix="1,0,0,-1,0,654.525" page="685"/><pgmtx matrix="1,0,0,-1,0,654.525" page="686"/><pgmtx matrix="1,0,0,-1,0,654.525" page="687"/><pgmtx matrix="1,0,0,-1,0,654.525" page="688"/><pgmtx matrix="1,0,0,-1,0,654.525" page="689"/><pgmtx matrix="1,0,0,-1,0,654.525" page="690"/><pgmtx matrix="1,0,0,-1,0,654.525" page="691"/><pgmtx matrix="1,0,0,-1,0,654.525" page="692"/><pgmtx matrix="1,0,0,-1,0,654.525" page="693"/><pgmtx matrix="1,0,0,-1,0,654.525" page="694"/><pgmtx matrix="1,0,0,-1,0,654.525" page="695"/><pgmtx matrix="1,0,0,-1,0,654.525" page="696"/><pgmtx matrix="1,0,0,-1,0,654.525" page="697"/><pgmtx matrix="1,0,0,-1,0,654.525" page="698"/><pgmtx matrix="1,0,0,-1,0,654.525" page="699"/><pgmtx matrix="1,0,0,-1,0,654.525" page="700"/><pgmtx matrix="1,0,0,-1,0,654.525" page="701"/><pgmtx matrix="1,0,0,-1,0,654.525" page="702"/><pgmtx matrix="1,0,0,-1,0,654.525" page="703"/><pgmtx matrix="1,0,0,-1,0,654.525" page="704"/><pgmtx matrix="1,0,0,-1,0,654.525" page="705"/><pgmtx matrix="1,0,0,-1,0,654.525" page="706"/><pgmtx matrix="1,0,0,-1,0,654.525" page="707"/><pgmtx matrix="1,0,0,-1,0,654.525" page="708"/><pgmtx matrix="1,0,0,-1,0,654.525" page="709"/><pgmtx matrix="1,0,0,-1,0,654.525" page="710"/><pgmtx matrix="1,0,0,-1,0,654.525" page="711"/><pgmtx matrix="1,0,0,-1,0,654.525" page="712"/><pgmtx matrix="1,0,0,-1,0,654.525" page="713"/><pgmtx matrix="1,0,0,-1,0,654.525" page="714"/><pgmtx matrix="1,0,0,-1,0,654.525" page="715"/><pgmtx matrix="1,0,0,-1,0,654.525" page="716"/><pgmtx matrix="1,0,0,-1,0,654.525" page="717"/><pgmtx matrix="1,0,0,-1,0,654.525" page="718"/><pgmtx matrix="1,0,0,-1,0,654.525" page="719"/><pgmtx matrix="1,0,0,-1,0,654.525" page="720"/><pgmtx matrix="1,0,0,-1,0,654.525" page="721"/><pgmtx matrix="1,0,0,-1,0,654.525" page="722"/><pgmtx matrix="1,0,0,-1,0,654.525" page="723"/><pgmtx matrix="1,0,0,-1,0,654.525" page="724"/><pgmtx matrix="1,0,0,-1,0,654.525" page="725"/><pgmtx matrix="1,0,0,-1,0,654.525" page="726"/><pgmtx matrix="1,0,0,-1,0,654.525" page="727"/></pages></xfdf>